qr_code_generator.py
qr_code_generator-0.1.0.dist-info/entry_points.txt
qr_code_generator-0.1.0.dist-info/WHEEL
qr_code_generator-0.1.0.dist-info/METADATA
qr_code_generator-0.1.0.dist-info/RECORD
