Metadata-Version: 2.1
Name: qr-code-generator
Version: 0.1.0
Summary: QR code generator for URLs i.e. dynamic QR codes.
License: MIT
Author: Marcelo Trylesinski
Author-email: marcelotryle@gmail.com
Requires-Python: >=3.8,<4.0
Classifier: License :: OSI Approved :: MIT License
Classifier: Programming Language :: Python :: 3
Classifier: Programming Language :: Python :: 3.8
Classifier: Programming Language :: Python :: 3.9
Requires-Dist: PyQRCode (>=1.2.1,<2.0.0)
Requires-Dist: typer (>=0.3.2,<0.4.0)
